specfile/__init__.py
specfile/changelog.py
specfile/conditions.py
specfile/constants.py
specfile/context_management.py
specfile/context_management.pyi
specfile/exceptions.py
specfile/formatter.py
specfile/macro_definitions.py
specfile/macros.py
specfile/options.py
specfile/prep.py
specfile/py.typed
specfile/sections.py
specfile/sourcelist.py
specfile/sources.py
specfile/spec_parser.py
specfile/specfile.py
specfile/tags.py
specfile/types.py
specfile/utils.py
specfile/value_parser.py
specfile-0.38.0.dist-info/licenses/LICENSE
specfile-0.38.0.dist-info/METADATA
specfile-0.38.0.dist-info/WHEEL
specfile-0.38.0.dist-info/top_level.txt
specfile-0.38.0.dist-info/RECORD
