Metadata-Version: 2.4
Name: specfile
Version: 0.38.0
Summary: A library for parsing and manipulating RPM spec files.
Home-page: https://github.com/packit/specfile
Author: Red Hat
Author-email: user-cont-team@redhat.com
License: MIT
Keywords: packaging,fedora,rpm,spec
Classifier: Development Status :: 4 - Beta
Classifier: Environment :: Console
Classifier: Intended Audience :: Developers
Classifier: License :: OSI Approved :: MIT License
Classifier: Operating System :: POSIX :: Linux
Classifier: Programming Language :: Python
Classifier: Programming Language :: Python :: 3
Classifier: Programming Language :: Python :: 3 :: Only
Classifier: Programming Language :: Python :: 3.6
Classifier: Programming Language :: Python :: 3.7
Classifier: Programming Language :: Python :: 3.8
Classifier: Programming Language :: Python :: 3.9
Classifier: Programming Language :: Python :: 3.10
Classifier: Programming Language :: Python :: 3.11
Classifier: Programming Language :: Python :: 3.12
Classifier: Topic :: Software Development
Classifier: Topic :: Utilities
Requires-Python: >=3.6
License-File: LICENSE
Requires-Dist: importlib-metadata; python_version < "3.8"
Requires-Dist: dataclasses; python_version < "3.7"
Requires-Dist: rpm
Requires-Dist: typing-extensions; python_version < "3.8"
Provides-Extra: testing
Requires-Dist: pytest; extra == "testing"
Requires-Dist: flexmock; extra == "testing"
Dynamic: license-file
